examples/__init__.py
examples/binding_example.py
examples/distributed_counter_example.py
examples/domain_primitive.py
examples/luggage_models.py
examples/next_gen.py
examples/quickstart_example.py
examples/relationship_example.py
examples/view_example.py
examples/city/__init__.py
examples/city/forms.py
examples/city/main.py
examples/city/mediators.py
examples/city/models.py
examples/city/tests.py
examples/city/views.py
examples/fluttergram/__init__.py
examples/fluttergram/domain_models/__init__.py
examples/fluttergram/domain_models/post.py
examples/fluttergram/domain_models/user.py
examples/fluttergram/tests/__init__.py
examples/fluttergram/tests/fixtures.py
examples/fluttergram/tests/test_delta_dav.py
examples/meeting_room/__init__.py
examples/meeting_room/graphql_quickstart.py
examples/meeting_room/quickstart.py
examples/meeting_room/domain_models/__init__.py
examples/meeting_room/domain_models/location.py
examples/meeting_room/domain_models/meeting.py
examples/meeting_room/domain_models/ticket.py
examples/meeting_room/domain_models/user.py
examples/meeting_room/tests/__init__.py
examples/meeting_room/tests/fixtures.py
examples/meeting_room/tests/main.py
examples/meeting_room/tests/test_dav.py
examples/meeting_room/tests/test_relationships.py
examples/meeting_room/tests/test_view_model.py
examples/meeting_room/view_models/__init__.py
examples/meeting_room/view_models/meeting_session.py
examples/meeting_room/view_models/user_view.py
examples/meeting_room/views/__init__.py
examples/meeting_room/views/graphql_view.py
examples/meeting_room/views/mediators.py
examples/meeting_room/views/meeting_session_ops.py
examples/meeting_room/views/rest_mediators.py
examples/probability/__init__.py
examples/probability/poisson.py
examples/ridesharing/__init__.py
onto/__init__.py
onto/auth.py
onto/collection_mixin.py
onto/common.py
onto/config.py
onto/context.py
onto/coordinator.py
onto/domain_model.py
onto/entity.py
onto/errors.py
onto/firestore_object.py
onto/flask-plugin.py
onto-0.0.8a19.dist-info/LICENSE
onto-0.0.8a19.dist-info/METADATA
onto-0.0.8a19.dist-info/WHEEL
onto-0.0.8a19.dist-info/top_level.txt
onto-0.0.8a19.dist-info/RECORD
