Metadata-Version: 2.1
Name: onto
Version: 0.0.8a19
Summary: Build reactive back end with ease 
Home-page: https://github.com/billyrrr/onto
Author: Bill Rao
Author-email: billrao@me.com
License: UNKNOWN
Keywords: firebase,firestore,ORM,flasgger,flask,backend,nosql,reactive,framework
Platform: UNKNOWN
Classifier: Development Status :: 4 - Beta
Classifier: Intended Audience :: Developers
Classifier: Programming Language :: Python :: 3.7
Classifier: Programming Language :: Python :: 3.8
Classifier: License :: OSI Approved :: MIT License
Classifier: Operating System :: OS Independent
License-File: LICENSE
Requires-Dist: Flask (>=0.10)
Requires-Dist: marshmallow
Requires-Dist: inflection
Requires-Dist: dictdiffer
Requires-Dist: iso8601
Requires-Dist: pyyaml
Requires-Dist: ProxyTypes
Requires-Dist: pymonad
Requires-Dist: pytz
Provides-Extra: celery
Requires-Dist: celery ; extra == 'celery'
Provides-Extra: couchbase
Requires-Dist: couchbase ; extra == 'couchbase'
Provides-Extra: couchdb
Requires-Dist: couchdb ; extra == 'couchdb'
Provides-Extra: firestore
Requires-Dist: google-auth ; extra == 'firestore'
Requires-Dist: google-api-python-client ; extra == 'firestore'
Requires-Dist: firebase-admin (>=3.0.0) ; extra == 'firestore'
Requires-Dist: google-cloud-firestore ; extra == 'firestore'
Requires-Dist: google-cloud-datastore ; extra == 'firestore'
Requires-Dist: grpcio (==1.30.0) ; extra == 'firestore'
Provides-Extra: flasgger
Requires-Dist: apispec (>=2.0.2) ; extra == 'flasgger'
Requires-Dist: flasgger ; extra == 'flasgger'
Provides-Extra: flask
Requires-Dist: flask-socketio ; extra == 'flask'
Provides-Extra: flink
Requires-Dist: apache-flink ; extra == 'flink'
Provides-Extra: gcloud
Requires-Dist: gitpython ; extra == 'gcloud'
Requires-Dist: google-cloud-logging ; extra == 'gcloud'
Provides-Extra: graphql
Requires-Dist: websockets ; extra == 'graphql'
Requires-Dist: starlette-graphql-zifulu ; extra == 'graphql'
Provides-Extra: jsonrpc
Requires-Dist: jsonrpcclient[requests] ; extra == 'jsonrpc'
Requires-Dist: Flask-JSONRPC ; extra == 'jsonrpc'
Provides-Extra: kafka
Requires-Dist: aiokafka ; extra == 'kafka'
Provides-Extra: leancloud
Requires-Dist: leancloud ; extra == 'leancloud'
Provides-Extra: pony
Requires-Dist: pony ; extra == 'pony'
Provides-Extra: rest_api
Requires-Dist: starlette ; extra == 'rest_api'
Provides-Extra: statefun
Requires-Dist: apache-flink-statefun (==3.2.0) ; extra == 'statefun'
